dynolayer/__init__.py
dynolayer/crud_mixin.py
dynolayer/dynolayer.py
dynolayer/utils.py
dynolayer-0.6.2.dist-info/licenses/LICENSE.txt
dynolayer-0.6.2.dist-info/METADATA
dynolayer-0.6.2.dist-info/WHEEL
dynolayer-0.6.2.dist-info/top_level.txt
dynolayer-0.6.2.dist-info/RECORD
