Metadata-Version: 2.4
Name: dynolayer
Version: 0.6.2
Summary: O DynoLayer é uma ferramenta poderosa que simplifica e agiliza o acesso e manipulação de dados no Amazon DynamoDB, baseada no padrão Active Record.
Home-page: https://github.com/kauelima21/dynolayer
Author: Kauê Leal de Lima
Author-email: kaueslim@gmail.com
License: MIT License
Keywords: dynolayer,dynamodb,active record,aws lambda
License-File: LICENSE.txt
Requires-Dist: pytz
Provides-Extra: aws
Requires-Dist: boto3; extra == "aws"
Dynamic: author
Dynamic: author-email
Dynamic: description
Dynamic: description-content-type
Dynamic: home-page
Dynamic: keywords
Dynamic: license
Dynamic: license-file
Dynamic: provides-extra
Dynamic: requires-dist
Dynamic: summary
